PyMQL5/PyMQL5.py
PyMQL5/Test.py
PyMQL5/Tools.py
PyMQL5/__init__.py
PyMQL5-1.2.0.dist-info/LICENSE
PyMQL5-1.2.0.dist-info/METADATA
PyMQL5-1.2.0.dist-info/WHEEL
PyMQL5-1.2.0.dist-info/top_level.txt
PyMQL5-1.2.0.dist-info/RECORD
