Metadata-Version: 2.1
Name: PyMQL5
Version: 1.2.0
Summary: O PyMQL5 é uma API que realiza a conexão entre Python3 e o Metatrader5 através de socket UDP.
Home-page: https://github.com/MaiconBaggio/PyMQL5
Author: Maicon D Baggio
Author-email: maionbaggio@outlook.com
License: MIT
Platform: UNKNOWN
Classifier: Intended Audience :: Developers
Classifier: License :: OSI Approved :: MIT License
Classifier: Natural Language :: Portuguese (Brazilian)
Classifier: Programming Language :: Python :: 3
